attachment_downloader/__init__.py
attachment_downloader/cli.py
attachment_downloader/encoding.py
attachment_downloader/logging.py
attachment_downloader/version.py
attachment_downloader/version_info.py
attachment_downloader-1.2.9.data/scripts/attachment-downloader
attachment_downloader-1.2.9.dist-info/licenses/LICENSE.txt
tests/__init__.py
tests/attachment_downloader/__init__.py
tests/attachment_downloader/test_cli.py
tests/attachment_downloader/test_encoding.py
attachment_downloader-1.2.9.dist-info/METADATA
attachment_downloader-1.2.9.dist-info/WHEEL
attachment_downloader-1.2.9.dist-info/top_level.txt
attachment_downloader-1.2.9.dist-info/RECORD
