Metadata-Version: 2.4
Name: attachment-downloader
Version: 1.2.9
Summary: Simple tool for downloading email attachments for all emails in a given folder using an IMAP client.
Home-page: https://github.com/jamesridgway/attachment-downloader
Author: James Ridgway
License: MIT
License-File: LICENSE.txt
Requires-Dist: assertpy==1.1
Requires-Dist: imbox==0.9.8
Requires-Dist: iso8601==2.1.0
Requires-Dist: jinja2==3.1.6
Requires-Dist: python-dateutil==2.9.0
Requires-Dist: pylint==3.3.7
Requires-Dist: pytest==8.4.0
Requires-Dist: pytest-cov==6.2.1
Requires-Dist: pytz==2025.2
Dynamic: author
Dynamic: description
Dynamic: home-page
Dynamic: license
Dynamic: license-file
Dynamic: requires-dist
Dynamic: summary
